py_alex_mess_server-0.1.1.data/scripts/server_run
server/__init__.py
server/server.py
server/common/__init__.py
server/common/decos.py
server/common/descrptrs.py
server/common/errors.py
server/common/metaclasses.py
server/common/utils.py
server/common/variables.py
server/log/__init__.py
server/log/client_config_log.py
server/log/server_config_log.py
server/server/__init__.py
server/server/add_user.py
server/server/config_window.py
server/server/core.py
server/server/database.py
server/server/main_window.py
server/server/remove_user.py
server/server/stat_window.py
server/unit_tests/__init__.py
py_alex_mess_server-0.1.1.dist-info/METADATA
py_alex_mess_server-0.1.1.dist-info/WHEEL
py_alex_mess_server-0.1.1.dist-info/top_level.txt
py_alex_mess_server-0.1.1.dist-info/RECORD
