Metadata-Version: 2.1
Name: py-alex-mess-server
Version: 0.1.1
Summary: Alex Mess Server
Home-page: UNKNOWN
Author: Alex
Author-email: momot-717@yandex.ru
License: UNKNOWN
Platform: UNKNOWN
Requires-Dist: PyQt5
Requires-Dist: sqlalchemy
Requires-Dist: pycryptodome
Requires-Dist: pycryptodomex
